{
    "openapi": "3.0.0",
    "info": {
        "title": "DIS MEDIA Store API",
        "description": "API Documentation for DIS MEDIA Store",
        "version": "1.0.0"
    },
    "paths": {
        "/api/products": {
            "get": {
                "tags": [
                    "Products"
                ],
                "summary": "Get all products",
                "operationId": "195e537590f1232e74d65ac201de3a65",
                "responses": {
                    "200": {
                        "description": "Successful operation",
                        "content": {
                            "application/json": {
                                "schema": {
                                    "type": "array",
                                    "items": {
                                        "$ref": "#/components/schemas/Product"
                                    }
                                }
                            }
                        }
                    }
                }
            },
            "post": {
                "tags": [
                    "Products"
                ],
                "summary": "Create a new product",
                "operationId": "6e243e8a40d71450f1f106e42ebb9d76",
                "requestBody": {
                    "required": true,
                    "content": {
                        "application/json": {
                            "schema": {
                                "$ref": "#/components/schemas/Product"
                            }
                        }
                    }
                },
                "responses": {
                    "201": {
                        "description": "Product created successfully",
                        "content": {
                            "application/json": {
                                "schema": {
                                    "$ref": "#/components/schemas/Product"
                                }
                            }
                        }
                    }
                }
            }
        },
        "/api/products/{id}": {
            "get": {
                "tags": [
                    "Products"
                ],
                "summary": "Get a specific product",
                "operationId": "e3ebdc71dd45bcbfc0137a33c58ae422",
                "parameters": [
                    {
                        "name": "id",
                        "in": "path",
                        "description": "Product ID",
                        "required": true,
                        "schema": {
                            "type": "integer"
                        }
                    }
                ],
                "responses": {
                    "200": {
                        "description": "Successful operation",
                        "content": {
                            "application/json": {
                                "schema": {
                                    "$ref": "#/components/schemas/Product"
                                }
                            }
                        }
                    },
                    "404": {
                        "description": "Product not found"
                    }
                }
            },
            "put": {
                "tags": [
                    "Products"
                ],
                "summary": "Update an existing product",
                "operationId": "db7d6b0e1397053fd4ab2047bca446bb",
                "parameters": [
                    {
                        "name": "id",
                        "in": "path",
                        "description": "Product ID",
                        "required": true,
                        "schema": {
                            "type": "integer"
                        }
                    }
                ],
                "requestBody": {
                    "required": true,
                    "content": {
                        "application/json": {
                            "schema": {
                                "$ref": "#/components/schemas/Product"
                            }
                        }
                    }
                },
                "responses": {
                    "200": {
                        "description": "Product updated successfully",
                        "content": {
                            "application/json": {
                                "schema": {
                                    "$ref": "#/components/schemas/Product"
                                }
                            }
                        }
                    },
                    "404": {
                        "description": "Product not found"
                    }
                }
            },
            "delete": {
                "tags": [
                    "Products"
                ],
                "summary": "Delete a product",
                "operationId": "60e9f0b40dfa3839a24fb67ebf8c6837",
                "parameters": [
                    {
                        "name": "id",
                        "in": "path",
                        "description": "Product ID",
                        "required": true,
                        "schema": {
                            "type": "integer"
                        }
                    }
                ],
                "responses": {
                    "204": {
                        "description": "Product deleted successfully"
                    },
                    "404": {
                        "description": "Product not found"
                    }
                }
            }
        }
    },
    "components": {
        "schemas": {
            "Product": {
                "required": [
                    "name",
                    "description",
                    "price",
                    "stock"
                ],
                "properties": {
                    "id": {
                        "type": "integer",
                        "readOnly": true,
                        "example": 1
                    },
                    "name": {
                        "type": "string",
                        "maxLength": 255,
                        "example": "T-Shirt DIS MEDIA"
                    },
                    "description": {
                        "type": "string",
                        "example": "Comfortable cotton t-shirt with DIS MEDIA logo"
                    },
                    "price": {
                        "type": "number",
                        "format": "float",
                        "example": 150000
                    },
                    "stock": {
                        "type": "integer",
                        "example": 100
                    },
                    "created_at": {
                        "type": "string",
                        "format": "date-time",
                        "readOnly": true
                    },
                    "updated_at": {
                        "type": "string",
                        "format": "date-time",
                        "readOnly": true
                    }
                },
                "type": "object"
            }
        }
    },
    "tags": [
        {
            "name": "Products",
            "description": "Products"
        }
    ]
}